LICENSE
README.md
pyproject.toml
setup.cfg
setup.py
src/graceful_exit/__init__.py
src/graceful_exit/helpers.py
src/graceful_exit/main.py
src/graceful_exit/module.py
src/graceful_exit/py.typed
src/graceful_exit.egg-info/PKG-INFO
src/graceful_exit.egg-info/SOURCES.txt
src/graceful_exit.egg-info/dependency_links.txt
src/graceful_exit.egg-info/not-zip-safe
src/graceful_exit.egg-info/requires.txt
src/graceful_exit.egg-info/top_level.txt
src/graceful_exit/custom_logger/__init__.py
src/graceful_exit/custom_logger/custom_logging.py
src/graceful_exit/exeptions/__init__.py
src/graceful_exit/exeptions/signal_exceptions.py
src/graceful_exit/typings/__init__.py
src/graceful_exit/typings/generics.py