Metadata-Version: 2.1
Name: graceful-exit
Version: 1.0.0
Summary: A flexible context manager for python to handle graceful termination of python programs
Author: Thim Lohse
License: MIT
Platform: unix
Platform: linux
Platform: osx
Platform: cygwin
Platform: win32
Classifier: License :: OSI Approved :: MIT License
Classifier: Programming Language :: Python :: 3
Classifier: Programming Language :: Python :: 3 :: Only
Classifier: Programming Language :: Python :: 3.9
Classifier: Programming Language :: Python :: 3.10
Requires-Python: >=3.9
Provides-Extra: testing
License-File: LICENSE
